redmibook_vpn/__init__.py
redmibook_vpn/__main__.py
redmibook_vpn/vpn_manager.py
redmibook_vpn-0.1.0.dist-info/METADATA
redmibook_vpn-0.1.0.dist-info/WHEEL
redmibook_vpn-0.1.0.dist-info/top_level.txt
redmibook_vpn-0.1.0.dist-info/RECORD
