Metadata-Version: 2.1
Name: redmibook_vpn
Version: 0.1.0
Summary: Пакет позволяющий использовать бесполезную кнопку на Redmibook pro 15, для подключения к VPN
Author-email: Savva Serebriakov <savva08savva08@gmail.com>
License: MIT
Requires-Python: >=3.8
Requires-Dist: evdev==1.4.0
